.gitignore
.readthedocs.yml
CITATION.cff
CODE_OF_CONDUCT.md
CONTRIBUTING.md
LICENSE
MANIFEST.in
NEWS
README.md
environment.yml
pyproject.toml
setup.cfg
setup.py
.github/workflows/continuous-integration-workflow.yml
.github/workflows/python-publish.yml
doc/Makefile
doc/conf.py
doc/faq.rst
doc/gethelp.py
doc/index.rst
doc/make.bat
doc/quick.rst
doc/segway.rst
doc/support.rst
doc/technical.rst
doc/troubleshooting.rst
docker/Dockerfile
segway/__init__.py
segway/_configparser.py
segway/_util.py
segway/bed.py
segway/include.py
segway/input_master.py
segway/layer.py
segway/observations.py
segway/output.py
segway/run.py
segway/structure.py
segway/task.py
segway/version.py
segway/winner.py
segway.egg-info/PKG-INFO
segway.egg-info/SOURCES.txt
segway.egg-info/dependency_links.txt
segway.egg-info/entry_points.txt
segway.egg-info/not-zip-safe
segway.egg-info/requires.txt
segway.egg-info/top_level.txt
segway/cluster/__init__.py
segway/cluster/common.py
segway/cluster/local.py
segway/cluster/lsf.py
segway/cluster/pbs.py
segway/cluster/sge.py
segway/cluster/sge_setup.py
segway/cluster/slurm.py
segway/data/__init__.py
segway/data/dinucleotide.tmpl
segway/data/dont_train.list
segway/data/input.master.tmpl
segway/data/map_frameIndex_ruler.dt.txt
segway/data/map_segTransition_ruler_seg_segCountDown_segCountDown.dt.tmpl
segway/data/map_seg_segCountDown.dt.tmpl
segway/data/map_seg_subseg_obs.dt.txt
segway/data/map_supervisionLabel_seg_alwaysTrue_semisupervised.dt.txt
segway/data/observation.tmpl
segway/data/output.master
segway/data/seg_table.tab
segway/data/segway-clean.sh
segway/data/segway-wrapper.sh
segway/data/segway.inc.tmpl
segway/data/segway.str.tmpl
segway/data/supervision.tmpl
segway/data/virtual_evidence.tmpl
test/README
test/clean.sh
test/compare_directory.py
test/test_all.sh
test/unit_tests.py
test/00-pyflakes/flymake-pyflakes.sh
test/00-pyflakes/run.sh
test/data/run.sh
test/data/seg_table_min_100.tab
test/data/test.genomedata
test/data/touchstone/identifydir/identify.tab
test/data/touchstone/identifydir/posterior0.bedGraph.gz
test/data/touchstone/identifydir/posterior1.bedGraph.gz
test/data/touchstone/identifydir/posterior2.bedGraph.gz
