Metadata-Version: 2.1
Name: segway
Version: 3.0.4
Summary: a way to segment the genome
Home-page: https://segway.hoffmanlab.org
Author: Michael Hoffman
Author-email: michael.hoffman@utoronto.ca
License: UNKNOWN
Download-URL: https://pypi.python.org/pypi/segway
Platform: UNKNOWN
Classifier: Natural Language :: English
Classifier: Development Status :: 5 - Production/Stable
Classifier: Intended Audience :: Science/Research
Classifier: License :: OSI Approved :: GNU General Public License v2 (GPLv2)
Classifier: Topic :: Scientific/Engineering :: Bio-Informatics
Classifier: Operating System :: Unix
Classifier: Programming Language :: Python
Classifier: Programming Language :: Python :: 2.7
Classifier: Programming Language :: Python :: 3
License-File: LICENSE
